{"expireTime":9007200886153241000,"key":"65cffbf5827eee3e5b7e8bd50769160b","val":{"name":"IMAGE_PROCESSING","inputPaths":["/Users/tay/Sites/shiren-5/content/images/monster/yamikichi.png"],"outputDir":"/Users/tay/Sites/shiren-5/public/static/e10dd6ad434230f77c3374a5cbe911d4","args":{"isLazy":false,"operations":[{"outputPath":"67e9d/yamikichi.png","args":{"width":78,"toFormat":"png","quality":100}}],"pluginOptions":{"base64Width":20,"forceBase64Format":"","useMozJpeg":false,"stripMetadata":true,"lazyImageGeneration":true,"defaultQuality":50,"failOnError":true,"plugins":[]}}}}