{"expireTime":9007200886151750000,"key":"293bece3fa87e7bbbd189df5278b6492","val":{"name":"IMAGE_PROCESSING","inputPaths":["/Users/tay/Sites/shiren-5/content/images/status/sleep.png"],"outputDir":"/Users/tay/Sites/shiren-5/public/static/de4279c25a08ac0d461f07dae7f3e9b3","args":{"isLazy":false,"operations":[{"outputPath":"67e9d/sleep.png","args":{"width":78,"toFormat":"png","quality":100}}],"pluginOptions":{"base64Width":20,"forceBase64Format":"","useMozJpeg":false,"stripMetadata":true,"lazyImageGeneration":true,"defaultQuality":50,"failOnError":true,"plugins":[]}}}}