{"expireTime":9007200886151751000,"key":"7fa3ba62b44878f9ddf213c63aa402fe","val":{"name":"IMAGE_PROCESSING","inputPaths":["/Users/tay/Sites/shiren-5/content/images/traps/spoil.png"],"outputDir":"/Users/tay/Sites/shiren-5/public/static/26cad678effefa31d8aa635f2be72cbc","args":{"isLazy":false,"operations":[{"outputPath":"c454d/spoil.png","args":{"width":27,"toFormat":"png","quality":100}}],"pluginOptions":{"base64Width":20,"forceBase64Format":"","useMozJpeg":false,"stripMetadata":true,"lazyImageGeneration":true,"defaultQuality":50,"failOnError":true,"plugins":[]}}}}